{
  "title": "雪の降る",
  "bpm": "120",
  "notes": [
    {
      "timing": "2294",
      "type": [
        ["0", "1", "0"],
        ["0", "1", "0"],
        ["0", "0", "0"]
      ],
      "character": "い"
    },
    {
      "timing": "2693",
      "type": [
        ["0", "1", "0"],
        ["0", "0", "1"],
        ["0", "1", "1"]
      ],
      "character": "ま"
    },
    {
      "timing": "3241",
      "type": [
        ["0", "0", "0"],
        ["0", "0", "0"],
        ["0", "1", "0"]
      ],
      "character": "わ"
    },
    {
      "timing": "3640",
      "type": [
        ["0", "1", "1"],
        ["0", "0", "1"],
        ["0", "0", "1"]
      ],
      "character": "す"
    },
    {
      "timing": "3889",
      "type": [
        ["0", "1", "1"],
        ["0", "1", "1"],
        ["0", "0", "0"]
      ],
      "character": "れ"
    },
    {
      "timing": "4089",
      "type": [
        ["0", "1", "0"],
        ["0", "0", "0"],
        ["0", "1", "0"]
      ],
      "character": "な"
    },
    {
      "timing": "4288",
      "type": [
        ["0", "1", "0"],
        ["0", "1", "0"],
        ["0", "0", "0"]
      ],
      "character": "い"
    },
    {
      "timing": "4590",
      "type": [
        ["0", "0", "1"],
        ["0", "0", "1"],
        ["0", "1", "0"]
      ],
      "character": "よ"
    },
    {
      "timing": "5585",
      "type": [
        ["0", "1", "0"],
        ["0", "0", "0"],
        ["0", "0", "0"]
      ],
      "character": "あ"
    },
    {
      "timing": "5784",
      "type": [
        ["0", "1", "0"],
        ["0", "0", "0"],
        ["0", "0", "0"]
      ],
      "character": "あ"
    },
    {
      "timing": "6383",
      "type": [
        ["0", "1", "0"],
        ["0", "1", "0"],
        ["0", "0", "0"]
      ],
      "character": "い"
    },
    {
      "timing": "6831",
      "type": [
        ["0", "1", "0"],
        ["0", "0", "1"],
        ["0", "1", "1"]
      ],
      "character": "ま"
    },
    {
      "timing": "7330",
      "type": [
        ["0", "0", "1"],
        ["0", "1", "0"],
        ["0", "0", "1"]
      ],
      "character": "こ"
    },
    {
      "timing": "7530",
      "type": [
        ["0", "0", "1"],
        ["0", "1", "0"],
        ["0", "1", "0"]
      ],
      "character": "の"
    },
    {
      "timing": "7829",
      "type": [
        ["0", "0", "1"],
        ["0", "1", "0"],
        ["0", "0", "0"]
      ],
      "character": "お"
    },
    {
      "timing": "7978",
      "type": [
        ["0", "0", "1"],
        ["0", "1", "1"],
        ["0", "1", "1"]
      ],
      "character": "も"
    },
    {
      "timing": "8278",
      "type": [
        ["0", "1", "0"],
        ["0", "1", "0"],
        ["0", "0", "0"]
      ],
      "character": "い"
    },
    {
      "timing": "9524",
      "type": [
        ["0", "1", "0"],
        ["0", "0", "0"],
        ["0", "0", "0"]
      ],
      "character": "あ"
    },
    {
      "timing": "9823",
      "type": [
        ["0", "1", "0"],
        ["0", "0", "0"],
        ["0", "0", "0"]
      ],
      "character": "あ"
    },
    {
      "timing": "10571",
      "type": [
        ["0", "0", "1"],
        ["0", "1", "1"],
        ["0", "1", "1"]
      ],
      "character": "も"
    },
    {
      "timing": "10821",
      "type": [
        ["0", "1", "1"],
        ["0", "0", "0"],
        ["0", "0", "0"]
      ],
      "character": "う"
    },
    {
      "timing": "11569",
      "type": [
        ["0", "1", "0"],
        ["0", "0", "0"],
        ["0", "1", "1"]
      ],
      "character": "は"
    },
    {
      "timing": "11818",
      "type": [
        ["0", "1", "0"],
        ["0", "0", "0"],
        ["0", "1", "0"]
      ],
      "character": "な"
    },
    {
      "timing": "11968",
      "type": [
        ["0", "1", "0"],
        ["0", "1", "1"],
        ["0", "0", "1"]
      ],
      "character": "し"
    },
    {
      "timing": "12317",
      "type": [
        ["0", "1", "0"],
        ["0", "0", "1"],
        ["0", "1", "0"]
      ],
      "character": "た"
    },
    {
      "timing": "12516",
      "type": [
        ["0", "1", "1"],
        ["0", "0", "0"],
        ["0", "0", "1"]
      ],
      "character": "く"
    },
    {
      "timing": "12715",
      "type": [
        ["0", "1", "0"],
        ["0", "0", "0"],
        ["0", "1", "0"]
      ],
      "character": "な"
    },
    {
      "timing": "13164",
      "type": [
        ["0", "1", "0"],
        ["0", "1", "0"],
        ["0", "0", "0"]
      ],
      "character": "い"
    },
    {
      "timing": "13364",
      "type": [
        ["0", "1", "0"],
        ["0", "0", "0"],
        ["0", "0", "0"]
      ],
      "character": "あ"
    },
    {
      "timing": "13864",
      "type": [
        ["0", "1", "0"],
        ["0", "0", "0"],
        ["0", "0", "0"]
      ],
      "character": "あ"
    },
    {
      "timing": "14660",
      "type": [
        ["0", "1", "0"],
        ["0", "1", "0"],
        ["0", "0", "0"]
      ],
      "character": "い"
    },
    {
      "timing": "15009",
      "type": [
        ["0", "1", "0"],
        ["0", "0", "1"],
        ["0", "1", "1"]
      ],
      "character": "ま"
    }
  ]
}
